CTkVisualizer/CTkVisualizer.py
CTkVisualizer/__init__.py
CTkVisualizer-1.0.8.dist-info/METADATA
CTkVisualizer-1.0.8.dist-info/WHEEL
CTkVisualizer-1.0.8.dist-info/top_level.txt
CTkVisualizer-1.0.8.dist-info/RECORD
