Metadata-Version: 2.1
Name: CTkVisualizer
Version: 1.0.8
Summary: A customtkinter widget for playing and visualizing Audio. 
Home-page: https://github.com/iLollek/CTkVisualizer
Author: iLollek
Author-email: loris_06@yahoo.de
Classifier: Programming Language :: Python :: 3
Classifier: License :: OSI Approved :: GNU General Public License v3 (GPLv3)
Classifier: Operating System :: OS Independent
Requires-Python: >=3.8
